cloudsearch/__init__.py
cloudsearch/_nbdev.py
cloudsearch/cloudsearch.py
cloudsearch-0.0.12.dist-info/LICENSE
cloudsearch-0.0.12.dist-info/METADATA
cloudsearch-0.0.12.dist-info/WHEEL
cloudsearch-0.0.12.dist-info/entry_points.txt
cloudsearch-0.0.12.dist-info/top_level.txt
cloudsearch-0.0.12.dist-info/RECORD
