Metadata-Version: 2.1
Name: cloudsearch
Version: 0.0.12
Summary: cloudsearch sdk for aws cloudsearch
Home-page: https://github.com/thanakijwanavit/cloudsearch/tree/master/
Author: Nic Wanavit
Author-email: nwanavit@hatari.cc
License: Apache Software License 2.0
Keywords: cloudsearch sdk
Platform: UNKNOWN
Classifier: Development Status :: 3 - Alpha
Classifier: Intended Audience :: Developers
Classifier: License :: OSI Approved :: Apache Software License
Classifier: Natural Language :: English
Classifier: Programming Language :: Python :: 3.6
Classifier: Programming Language :: Python :: 3.7
Classifier: Programming Language :: Python :: 3.8
Requires-Python: >=3.6
Requires-Dist: boto3
Requires-Dist: pandas
